{"projectId":"Photo","suiteId":"0001","prId":"pr-002","beforeVersion":1,"date":1554668800609,"type":"success","hasPassed":false,"hasFailed":false,"hasNew":true,"hasDeleted":false,"newItems":[{"raw":"sample.1.png","encoded":"sample.1.png","hasMask":false},{"raw":"sample.2.should_be_2_but_1_in_before.png","encoded":"sample.2.should_be_2_but_1_in_before.png","hasMask":false},{"raw":"sample0.1.png","encoded":"sample0.1.png","hasMask":false},{"raw":"sample0.2.should_be_2_but_1_in_before.png","encoded":"sample0.2.should_be_2_but_1_in_before.png","hasMask":false},{"raw":"sample1.1.png","encoded":"sample1.1.png","hasMask":false},{"raw":"sample1.2.should_be_2_but_1_in_before.png","encoded":"sample1.2.should_be_2_but_1_in_before.png","hasMask":false},{"raw":"sample2.1.png","encoded":"sample2.1.png","hasMask":false},{"raw":"sample2.2.should_be_2_but_1_in_before.png","encoded":"sample2.2.should_be_2_but_1_in_before.png","hasMask":false},{"raw":"sample3.1.png","encoded":"sample3.1.png","hasMask":false},{"raw":"sample4.1.png","encoded":"sample4.1.png","hasMask":false},{"raw":"sample5.1.png","encoded":"sample5.1.png","hasMask":false},{"raw":"sample6.1.png","encoded":"sample6.1.png","hasMask":false}],"deletedItems":[],"passedItems":[],"failedItems":[],"actualDir":"./public/Photo-0001/pr-002/after","expectedDir":"./public/Photo-0001/before","diffDir":"./public/Photo-0001/pr-002/diff","ximgdiffConfig":{"enabled":false,"workerUrl":"./worker.js"}}